plover_dictionary_builder/__init__.py
plover_dictionary_builder/dictionary_builder.py
plover_dictionary_builder/dictionary_builder_ui.py
plover_dictionary_builder/resources_rc.py
plover_dictionary_builder-0.1.0.dist-info/METADATA
plover_dictionary_builder-0.1.0.dist-info/WHEEL
plover_dictionary_builder-0.1.0.dist-info/entry_points.txt
plover_dictionary_builder-0.1.0.dist-info/top_level.txt
plover_dictionary_builder-0.1.0.dist-info/zip-safe
plover_dictionary_builder-0.1.0.dist-info/RECORD
